{
  "indexes": [
    {
      "collectionGroup": "schedules",
      "queryScope": "COLLECTION",
      "fields": [
        {
          "fieldPath": "recurringGroupId",
          "order": "ASCENDING"
        },
        {
          "fieldPath": "startDate",
          "order": "ASCENDING"
        }
      ]
    },
    {
      "collectionGroup": "schedules",
      "queryScope": "COLLECTION",
      "fields": [
        {
          "fieldPath": "startDate",
          "order": "ASCENDING"
        },
        {
          "fieldPath": "endDate",
          "order": "ASCENDING"
        }
      ]
    },
    {
      "collectionGroup": "diary",
      "queryScope": "COLLECTION",
      "fields": [
        {
          "fieldPath": "created_date",
          "order": "ASCENDING"
        },
        {
          "fieldPath": "created_at",
          "order": "DESCENDING"
        }
      ]
    },
    {
      "collectionGroup": "memos",
      "queryScope": "COLLECTION",
      "fields": [
        {
          "fieldPath": "isPinned",
          "order": "DESCENDING"
        },
        {
          "fieldPath": "updatedAt",
          "order": "DESCENDING"
        }
      ]
    },
    {
      "collectionGroup": "todos",
      "queryScope": "COLLECTION",
      "fields": [
        {
          "fieldPath": "isCompleted",
          "order": "ASCENDING"
        },
        {
          "fieldPath": "createdAt",
          "order": "DESCENDING"
        }
      ]
    }
  ],
  "fieldOverrides": []
}